{
    "type": "flex",
    "altText": "[Web開発][AI][クラウド] 【Zenn トレンド記事】SnowflakeとDatabricksの機能をそれぞれ見てみる",
    "contents": {
        "type": "bubble",
        "styles": {
            "header": {
                "backgroundColor": "#1E2A38"
            },
            "body": {
                "backgroundColor": "#2D3748"
            },
            "footer": {
                "backgroundColor": "#2D3748",
                "separator": true,
                "separatorColor": "#4A5568"
            }
        },
        "header": {
            "type": "box",
            "layout": "vertical",
            "contents": [
                {
                    "type": "text",
                    "text": "[ Zenn トレンド記事 ]",
                    "weight": "bold",
                    "color": "#1DB446",
                    "size": "sm"
                }
            ],
            "paddingAll": "12px"
        },
        "body": {
            "type": "box",
            "layout": "vertical",
            "spacing": "md",
            "contents": [
                {
                    "type": "text",
                    "text": "SnowflakeとDatabricksの機能をそれぞれ見てみる",
                    "weight": "bold",
                    "size": "xl",
                    "wrap": true,
                    "color": "#FFFFFF"
                },
                {
                    "type": "box",
                    "layout": "horizontal",
                    "contents": [
                        {
                            "type": "box",
                            "layout": "vertical",
                            "backgroundColor": "#4A5568",
                            "cornerRadius": "md",
                            "paddingAll": "6px",
                            "contents": [
                                {
                                    "type": "text",
                                    "text": "Web開発",
                                    "color": "#FFFFFF",
                                    "size": "xs",
                                    "weight": "bold",
                                    "align": "center"
                                }
                            ],
                            "action": {
                                "type": "message",
                                "label": "Web開発",
                                "text": "Web開発に関する記事"
                            }
                        },
                        {
                            "type": "box",
                            "layout": "vertical",
                            "backgroundColor": "#4A5568",
                            "cornerRadius": "md",
                            "paddingAll": "6px",
                            "contents": [
                                {
                                    "type": "text",
                                    "text": "AI",
                                    "color": "#FFFFFF",
                                    "size": "xs",
                                    "weight": "bold",
                                    "align": "center"
                                }
                            ],
                            "action": {
                                "type": "message",
                                "label": "AI",
                                "text": "AIに関する記事"
                            }
                        },
                        {
                            "type": "box",
                            "layout": "vertical",
                            "backgroundColor": "#4A5568",
                            "cornerRadius": "md",
                            "paddingAll": "6px",
                            "contents": [
                                {
                                    "type": "text",
                                    "text": "クラウド",
                                    "color": "#FFFFFF",
                                    "size": "xs",
                                    "weight": "bold",
                                    "align": "center"
                                }
                            ],
                            "action": {
                                "type": "message",
                                "label": "クラウド",
                                "text": "クラウドに関する記事"
                            }
                        }
                    ],
                    "spacing": "sm",
                    "margin": "lg"
                },
                {
                    "type": "text",
                    "text": "2025\/09\/20 12:11",
                    "wrap": true,
                    "size": "sm",
                    "color": "#A0AEC0",
                    "margin": "lg"
                },
                {
                    "type": "box",
                    "layout": "vertical",
                    "margin": "lg",
                    "spacing": "sm",
                    "contents": [
                        {
                            "type": "box",
                            "layout": "baseline",
                            "spacing": "sm",
                            "contents": [
                                {
                                    "type": "text",
                                    "text": "Summary",
                                    "color": "#A0AEC0",
                                    "size": "sm",
                                    "flex": 0
                                }
                            ]
                        },
                        {
                            "type": "text",
                            "text": "SnowflakeとDatabricksは、それぞれクラウドベースのデータウェアハウスとデータ分析・AIプラットフォームです。Snowflakeは高速なデータ集計とガバナンスに優れ、DatabricksはApache Sparkを基盤とし、データエンジニアリングから機械学習までを統合的に実行できます。両者はデータ形式、ストレージ方式、外部データ接続、データ管理、データ共有において異なる特徴を持ち、企業のニーズに合わせて選択または併用できます。",
                            "wrap": true,
                            "size": "sm",
                            "margin": "md",
                            "color": "#E2E8F0"
                        }
                    ]
                },
                {
                    "type": "separator",
                    "margin": "xl"
                },
                {
                    "type": "text",
                    "text": "今日のテッククイズ💡",
                    "weight": "bold",
                    "size": "md",
                    "margin": "lg",
                    "color": "#1DB446"
                },
                {
                    "type": "text",
                    "text": "Databricksの基盤となっているのは次のうちどれですか？",
                    "wrap": true,
                    "size": "sm",
                    "color": "#E2E8F0",
                    "margin": "md"
                },
                {
                    "type": "box",
                    "layout": "vertical",
                    "spacing": "sm",
                    "margin": "md",
                    "contents": [
                        {
                            "type": "button",
                            "action": {
                                "type": "postback",
                                "label": "Apache Hadoop",
                                "data": "action=quiz_answer&is_correct=0&correct_answer=Apache+Spark",
                                "displayText": "Apache Hadoop"
                            },
                            "style": "secondary",
                            "height": "sm",
                            "margin": "sm"
                        },
                        {
                            "type": "button",
                            "action": {
                                "type": "postback",
                                "label": "Apache Spark",
                                "data": "action=quiz_answer&is_correct=1&correct_answer=Apache+Spark",
                                "displayText": "Apache Spark"
                            },
                            "style": "secondary",
                            "height": "sm",
                            "margin": "sm"
                        },
                        {
                            "type": "button",
                            "action": {
                                "type": "postback",
                                "label": "TensorFlow",
                                "data": "action=quiz_answer&is_correct=0&correct_answer=Apache+Spark",
                                "displayText": "TensorFlow"
                            },
                            "style": "secondary",
                            "height": "sm",
                            "margin": "sm"
                        }
                    ]
                }
            ]
        },
        "footer": {
            "type": "box",
            "layout": "vertical",
            "spacing": "sm",
            "contents": [
                {
                    "type": "button",
                    "action": {
                        "type": "uri",
                        "label": "記事を読む",
                        "uri": "https:\/\/zenn.dev\/kou_zenn\/articles\/50bc3151ef2326"
                    },
                    "style": "primary",
                    "height": "sm",
                    "color": "#4A5568"
                }
            ],
            "flex": 0
        },
        "hero": {
            "type": "image",
            "url": "https:\/\/logo.svgcdn.com\/s\/zenn-dark.png",
            "size": "full",
            "aspectRatio": "20:13",
            "aspectMode": "cover"
        }
    }
}